npyodbc-5.3.0.0.dist-info/METADATA
npyodbc-5.3.0.0.dist-info/WHEEL
npyodbc-5.3.0.0.dist-info/LICENSE
npyodbc.cp314-win_arm64.pyd
npyodbc.cp314-win_arm64.lib
npyodbc-5.3.0.0.dist-info/RECORD
