Metadata-Version: 2.1
Name: npyodbc
Version: 5.3.0.0
Summary: pyodbc extended to use NumPy
Author-Email: Quansight <connect@quansight.com>
License: BSD 3-Clause License
Project-URL: Source, https://github.com/Quansight/npyodbc
Requires-Python: >=3.9
Requires-Dist: numpy>=1.26.2
Provides-Extra: dev
Requires-Dist: pre-commit; extra == "dev"
Requires-Dist: meson-python; extra == "dev"
Provides-Extra: test
Requires-Dist: pytest; extra == "test"
Requires-Dist: hypothesis; extra == "test"
